Metadata-Version: 2.1
Name: netapp-api
Version: 1.0.1
Summary: NetApp OCUM API wrapper
Home-page: https://github.com/cerndb/netapp-api-python
Author: CERN
Author-email: ignacio.coterillo@cern.ch
Maintainer: Ignacio Coterillo
Maintainer-email: ignacio.coterillo@cern.ch
License: GPLv3
Platform: UNKNOWN
Classifier: Development Status :: 4 - Beta
Classifier: Intended Audience :: Developers
Classifier: Programming Language :: Python :: 2.7
Classifier: Programming Language :: Python :: 3
